{
  "id": 0,
  "parent_id": -1,
  "name": "Root",
  "data": "",
  "children": {
    "14": {
      "id": 14,
      "parent_id": 0,
      "name": "note 1",
      "data": "",
      "children": {
        "21": {
          "id": 21,
          "parent_id": 14,
          "name": "note 1-1",
          "data": "",
          "children": {},
          "is_expanded": false
        }
      },
      "is_expanded": true
    },
    "16": {
      "id": 16,
      "parent_id": 0,
      "name": "note 2",
      "data": "",
      "children": {
        "17": {
          "id": 17,
          "parent_id": 16,
          "name": "note 2-2",
          "data": "",
          "children": {},
          "is_expanded": false
        }
      },
      "is_expanded": true
    }
  },
  "is_expanded": true
}